Workbook

Sheet Inputs
A1: SunEnergy Value | D1: Input Information
C3: Parameters | D3: Value | E3: Units
C5: Annual Units Consumed | D5: 6665 | E5: kWh/year
C6: Monthly Units Consumed | D6: =(D5/12) -> 555.41667 | E6: kWh/month
C7: Daily Units / Daily Load | D7: =(D6/30) -> 18.513889 | E7: kWh/day
C8: Location | D8: Islamabad
C9: Peak Sun Hours | D9: 6.4 | E9: hrs.
C10: System Efficiency | D10: 0.8
C11: System Size | D11: =(D7/(D9 * D10)) * 1.75 -> 6.3279894 | E11: kW
C12: Solar Size | D12: 1435 | E12: W
C15: Carbon Dioxide Emitted | D15: 0.5 | E15: kg/kWh

Sheet Technical
A1: SunEnergy Value | D1: Technical Results
C3: Parameters | E3: Results | F3: Units
C5: Annual Energy Production | E5: =(E6 * 12) -> 14579.687 | F5: kWh/Year
C6: Monthly Energy Production | E6: =(E7 * 30) -> 1214.974 | F6: kWh/month
C7: Daily Energy Production | E7: =(Inputs!D11 * Inputs!D9) -> 40.499132 | F7: kWh/day
C8: Panels Required | E8: =(Inputs!D11 * 1000) / Inputs!D12 -> 4.4097487
C9: Inverter Size | E9: =(Inputs!D11 * 1.5) -> 9.491984 | F9: kW
C11: Excess Units (Export to Grid) | E11: =(E5 - Inputs!D5) -> 7914.6875 | F11: kWh/year
C14: Reduced Carbon Dioxide Emission | E14: =E5 * Inputs!D15 -> 7289.8437 | F14: kg
C15: 25-Year Carbon Dioxide Emission | E15: =E14 * 25 -> 182246.09 | F15: kg

Sheet Financial
A1: SunEnergy Value | D1: Financial Analysis
C3: Parameters | D3: Results | E3: Units | F3: Items | G3: Results | H3: Units
C5: Panel Cost | D5: =(Inputs!D11 * G14) -> 1107398.1 | E5: Rs. | F5: Save Bill Money | G5: =(Inputs!D5 * G12) -> 266600 | H5: Rs./Year
C6: Inverter Cost | D6: 140000 | E6: Rs. | F6: Earn Money by sell units | G6: =(Technical!E11 * G13) -> 158293.75 | H6: Rs./Year
C7: Structure & Frame Cost | D7: 60000 | E7: Rs. | F7: Annual Savings | G7: =SUM(G5:G6) -> 424893.75 | H7: Rs./Year
C8: On-Grid (Net Metering) | D8: 65000 | E8: Rs. | F8: Payback Period | G8: =D10/G7 -> 3.3241208 | H8: Years
C9: Total Labor Cost | D9: 40000 | E9: Rs. | F9: ROI | G9: =(1/G8) * 100 -> 30.083143 | H9: %/Year
C10: Total System Cost | D10: =SUM(D5:D9) -> 1412398.1 | E10: Rs. | F10: ="This system covers initial investment in "& ROUND(G8,1) &" Years & gives free electricity in next "& ROUND(D12-G8,1) &" Years." -> This system covers initial investment in 3.3 Years & gives free electricity in next 21.7 Years.
F11: Data | G11: Values
C12: Total System Life Span | D12: 25 | E12: Years | F12: Tarrif Rate. (Rs) / Unit | G12: 40
F13: Export Rate (Rs) / Unit | G13: 20
F14: Cost per kW | G14: 175000

Sheet Environmental
A1: SunEnergy Value | B1: #VALUE!
A3: Sustainable Environment
A4: Parameters | B4: Value | C4: Units
A5: Reduce Carbon Dioxide Emission | B5: =Technical!E14 -> 7289.8437 | C5: kg/year
A6: 25-Year Carbon Dioxide Emission Reduce | B6: =Technical!E15 -> 182246.09 | C6: kg
A7: 1 Tree Absorbs Carbon dioxide | B7: 21 | C7: kg/year
A8: Sustainable Impact | B8: =B5/B7 -> 347.13542 | C8: (Total Save Trees)
A9: Result: | B9: ="The PV Solar System will reduce "& ROUND(B5,1) &" kg/Year that enhances the sustainable environment. Reduction of Carbon dioxide annually will implant total "& ROUND(B8,1) &" trees." -> The PV Solar System will reduce 7289.8 kg/Year that enhances the sustainable environment. Reduction of Carbon dioxide annually will implant total 347.1 trees.

Sheet Visual Dashboard
A1: SunEnergy Value | B1: #VALUE! | D1: System Status: | E1: =IF(Financial!G8<=6, "Highly Recommended", IF(Financial!G8<=8.8, "Moderate", "Not Recommended")) -> Highly Recommended | K1: Graphical Results
C2: Solar PV System & Financial Report Analysis
A3: DATE: | B3: =TODAY() -> 46075
A4: Given Details | E4: System Output Idea | I4: Energy Production
A5: Parameters | B5: Value | C5: Units | E5: Paramters | F5: Value | G5: Units | I5: Paramters | J5: Value | K5: Units
A6: Yearly units Consumed | B6: =Inputs!D5 -> 6665 | C6: kWh/year | E6: For Solar Watts (W) | F6: =Inputs!D12 -> 1435 | G6: W | I6: Annual Energy Generation | J6: =Technical!E5 -> 14579.687 | K6: kWh/year
A7: Monthly Units Consumed | B7: =Inputs!D6 -> 555.41667 | C7: kWh/month | E7: Solar System Size | F7: =Inputs!D11 -> 6.3279894 | G7: kW | I7: Monthly Energy Generation | J7: =Technical!E6 -> 1214.974 | K7: kWh/month
A8: Daily Units Consumed | B8: =Inputs!D7 -> 18.513889 | C8: kWh/day | E8: No. Of Panels Required | F8: =Technical!E8 -> 4.4097487 | I8: Daily Energy Generation | J8: =Technical!E7 -> 40.499132 | K8: kWh/day
A9: Location | B9: PAKISTAN | E9: CostperkW | F9: =Financial!G14 -> 175000 | G9: Rs.
A10: Peak Sun Hours | B10: =Inputs!D9 -> 6.4 | C10: hrs. | E10: Total Panels Cost | F10: =Financial!D5 -> 1107398.1 | G10: Rs. | I10: Excess Energy/Units Generate | J10: =Technical!E11 -> 7914.6875 | K10: kWh/year
A11: System Efficiency | B11: =Inputs!D10 -> 0.8 | E11: Inverter Size | F11: =Technical!E9 -> 9.491984 | G11: kW
A14: Investment & Coverage
A15: Parameters | B15: Value | C15: Units
A16: Total System Cost Required | B16: =Financial!D10 -> 1412398.1 | C16: Rs.
A17: Tarriff Rate | B17: =Financial!G12 -> 40 | C17: Rs./Unit
A18: WAPDA Bill Cut-off Price | B18: =Financial!G5 -> 266600 | C18: Rs.
A19: Export Unit Rate | B19: =Financial!G13 -> 20 | C19: Rs./Unit
A20: Earn Money from Export Units | B20: =Financial!G6 -> 158293.75 | C20: Rs.
A21: Total Save Money | B21: =Financial!G7 -> 424893.75 | C21: Rs.
A23: Payback Period | B23: =Financial!G8 -> 3.3241208 | C23: Years
A24: ROI | B24: =Financial!G9 -> 30.083143 | C24: %/Year
A26: Daily Coverage | B26: =(B8/J8) * 100 -> 45.714286 | C26: %/day
A28: Sustainable Environment | E28: Final Verdict | F28: This PV System calculations and analysis is estimated based on "Pakistan" assumptions. It may varies and get real-time idea by visit the site with all scenarios will be considered.
A29: Parameters | B29: Value | C29: Units
A30: Reduce Carbon Dioxide Emission | B30: =Technical!E14 -> 7289.8437 | C30: kg
A31: 25-Year Carbon Dioxide Emission Reduce | B31: =Technical!E15 -> 182246.09 | C31: kg

Sheet Feasible
A1: SunEnergy Value | B1: #VALUE!
A3: Check (NPV) Feasiblity | C3: In this sheet, we check the feasibility behaviour of our system. That, tells our investment in safe hand or not?
A6: Data | B6: Value | C6: Description
A7: Discount Rate (r) | B7: 0.1 | C7: If I put my investment in bank, then per year it gives me 10% profit which is known as "Bench mark". We compare both senarios, to deposit money in bank vs investment in installed solar system.
A8: Annual Savings (Includes bill saving + Export Units Revenue) Money | B8: =Financial!G7 -> 424893.75
A9: Operating & Maintenace Cost (For System) | B9: =(B8/10) -> 42489.375
A10: Initial Investment (Total System Cost) | B10: =Financial!D10 -> 1412398.1
A11: Total Cash Flow | B11: =(B8 - B9) -> 382404.37
A12: NPV (Net Present Value) | B12: =(B11 / (1+B7)^32) - B10 -> -1394286.5
A14: Final Remarks | B14: =IF(B12>0, "Feasible", IF(B12=0, "Break Even", "Not Feasible")) -> Not Feasible
A16: Check IRR | C16: Actual rate of return, in which net present value equals to zero. The system is feasible only, if IRR greater than discount rate.
A18: NPV | B18: 0
A19: Total Cash Flow | B19: =B11 -> 382404.37
A20: Initial Investment (Total System Cost) | B20: =B10 -> 1412398.1
A21: IRR | B21: =(((B19/B20)^(1/32)) - 1) * 100 -> -4.0007857
A23: Final Remarks | B23: =IF(B21>B7, "Feasible", IF(B21=B7, "Break Even", "Not Feasible")) -> Not Feasible
A25: Check LCOE | C25: Check the levelized Cost of Energy, gives an idea how much charge our system gives 1 Unit(kWh) cost and compare with grid tarriff rate.
A26: Data | B26: Value | C26: Units
A27: Total Life Cycle of solar system | B27: =Financial!D12 -> 25 | C27: Years
A28: Annually Units/Energy Generation | B28: =Technical!E5 -> 14579.687 | C28: kWh/Year
A29: Total Life-Time Units/Energy Generation | B29: =(B28 * B27) -> 364492.19 | C29: kWh/Life-Time
A31: LCOE | B31: =(B20/B29) -> 3.8749751 | C31: Rs.
A32: Check Tarriff Rate
A33: Data | B33: Value | C33: Units
A34: Tarriff Rate In Pakistan | B34: 40 | C34: Rs.
A36: Final Remarks | B36: =IF(B31<B34, "Feasible", IF(B31=B34, "Break Even", "Not Feasible")) -> Feasible
A38: Environmental Monetization
A39: Data | B39: Value | C39: Units
A40: 1 Ton | B40: 1000 | C40: kg
A41: Reduced Carbon Dioxide Emission Annually | B41: =Technical!E5 * Inputs!D15 -> 7289.8437 | C41: kg/kWh/Year
A42: 25 -Year Reduced Carbon Dioxide Emission | B42: =Feasible!B41 * 25 -> 182246.09 | C42: kg/kWh/25Years
A43: 1 Ton Carbon Dioxide Reduced Price | B43: 2800 | C43: Rs.
A44: Annually Carbon Credit
A45: How much ton your system reduced carbon dioxide emission annually | B45: =(B41/B40) -> 7.2898437 | C45: Ton
A46: Carbon Credit Price for your system | B46: =(B45 * B43) -> 20411.562 | C46: Rs./Year
A47: Over 25 Years
A48: How much ton your system reduced carbon dioxide emission over 25Years | B48: =(B42/B40) -> 182.24609 | C48: Ton
A49: Carbon Credit Price for your system | B49: =(B48 * B43) -> 510289.06 | C49: Rs. / Year

Sheet Scoring
A1: SunEnergy Value | B1: #VALUE!
B4: Sustainability Factors
A5: Factors | B5: Values | C5: Units | D5: Score
A6: Carbon Dioxide Emission Annually | B6: =Environmental!B5 -> 7289.8437 | C6: kg/Year | D6: =IF(B6<200, 25, IF(B6<=500, 50, IF(B6<=1000, 75, 100))) -> 100
A7: For 25 Years Carbon Dioxide Emission | B7: =Environmental!B6 -> 182246.09 | C7: kg/25Year | D7: =IF(B7<5000, 25, IF(B7<=7500, 50, IF(B7<=10000, 75, 100))) -> 100
A8: Renewable Solar Load Coverage | B8: ='Visual Dashboard'!B26 -> 45.714286 | C8: %/day | D8: =IF(B8<30, 25, IF(B8<=60, 50, IF(B8<=90, 75, 100))) -> 50
A9: LCOE vs Grid Tarriff Rate | B9: =(Feasible!B31 / Feasible!B34) * 100 -> 9.6874377 | C9: Difference (Solar unit cost / Grid Tarriff unit cost) | D9: =IF(B9<5, 25, IF(B9<=15, 50, IF(B9<=25, 75, 100))) -> 50
B11: Sustainability Index | C11: =SUM(D6:D9) / 4 -> 75 | D11: =IF(C11<60, "Low Sustainable", IF(C11<=75, "Moderate Sustainable", "Highly Sustainable")) -> Moderate Sustainable
