Workbook

Sheet Inputs
A1: SunEnergy Value | D1: Input Information
C3: Parameters | D3: Value | E3: Units
C5: Annual Units Consumed | D5: 365 | E5: kWh/year
C6: Monthly Units Consumed | D6: =(D5/12) -> 30.416667 | E6: kWh/month
C7: Daily Units / Daily Load | D7: =(D6/30) -> 1.0138889 | E7: kWh/day
C8: Location | D8: Islamabad
C9: Peak Sun Hours | D9: 5 | E9: hrs.
C10: System Efficiency | D10: 0.8
C11: System Size | D11: =(D7/(D9 * D10)) * 1.75 -> 0.44357639 | E11: kW
C12: Solar Size | D12: 550 | E12: W
C15: Carbon Dioxide Emitted | D15: 0.5 | E15: kg/kWh

Sheet Technical
A1: SunEnergy Value | D1: Technical Results
C3: Parameters | E3: Results | F3: Units
C5: Annual Energy Production | E5: =(E6 * 12) -> 798.4375 | F5: kWh/Year
C6: Monthly Energy Production | E6: =(E7 * 30) -> 66.536458 | F6: kWh/month
C7: Daily Energy Production | E7: =(Inputs!D11 * Inputs!D9) -> 2.2178819 | F7: kWh/day
C8: Panels Required | E8: =(Inputs!D11 * 1000) / Inputs!D12 -> 0.80650253
C9: Inverter Size | E9: =(Inputs!D11 * 1.5) -> 0.66536458 | F9: kW
C11: Excess Units (Export to Grid) | E11: =(E5 - Inputs!D5) -> 433.4375 | F11: kWh/year
C14: Reduced Carbon Dioxide Emission | E14: =E5 * Inputs!D15 -> 399.21875 | F14: kg
C15: 25-Year Carbon Dioxide Emission | E15: =E14 * 25 -> 9980.4688 | F15: kg

Sheet Financial
A1: SunEnergy Value | D1: Financial Analysis
C3: Parameters | D3: Results | E3: Units | F3: Items | G3: Results | H3: Units
C5: Panel Cost | D5: =(Inputs!D11 * G14) -> 77625.868 | E5: Rs. | F5: Save Bill Money | G5: =(Inputs!D5 * G12) -> 14600 | H5: Rs./Year
C6: Inverter Cost | D6: 140000 | E6: Rs. | F6: Earn Money by sell units | G6: =(Technical!E11 * G13) -> 8668.75 | H6: Rs./Year
C7: Structure & Frame Cost | D7: 60000 | E7: Rs. | F7: Annual Savings | G7: =SUM(G5:G6) -> 23268.75 | H7: Rs./Year
C8: On-Grid (Net Metering) | D8: 65000 | E8: Rs. | F8: Payback Period | G8: =D10/G7 -> 16.443765 | H8: Years
C9: Total Labor Cost | D9: 40000 | E9: Rs. | F9: ROI | G9: =(1/G8) * 100 -> 6.0813322 | H9: %/Year
C10: Total System Cost | D10: =SUM(D5:D9) -> 382625.87 | E10: Rs. | F10: ="This system covers initial investment in "& ROUND(G8,1) &" Years & gives free electricity in next "& ROUND(D12-G8,1) &" Years." -> This system covers initial investment in 16.4 Years & gives free electricity in next 8.6 Years.
F11: Data | G11: Values
C12: Total System Life Span | D12: 25 | E12: Years | F12: Tarrif Rate. (Rs) / Unit | G12: 40
F13: Export Rate (Rs) / Unit | G13: 20
F14: Cost per kW | G14: 175000

Sheet Environmental
A1: SunEnergy Value | B1: #VALUE!
A3: Sustainable Environment
A4: Parameters | B4: Value | C4: Units
A5: Reduce Carbon Dioxide Emission | B5: =Technical!E14 -> 399.21875 | C5: kg/year
A6: 25-Year Carbon Dioxide Emission Reduce | B6: =Technical!E15 -> 9980.4688 | C6: kg
A7: 1 Tree Absorbs Carbon dioxide | B7: 21 | C7: kg/year
A8: Sustainable Impact | B8: =B5/B7 -> 19.010417 | C8: (Total Save Trees)
A9: Result: | B9: ="The PV Solar System will reduce "& ROUND(B5,1) &" kg/Year that enhances the sustainable environment. Reduction of Carbon dioxide annually will implant total "& ROUND(B8,1) &" trees." -> The PV Solar System will reduce 399.2 kg/Year that enhances the sustainable environment. Reduction of Carbon dioxide annually will implant total 19 trees.

Sheet Visual Dashboard
A1: SunEnergy Value | B1: #VALUE! | D1: System Status: | E1: =IF(Financial!G8<=6, "Highly Recommended", IF(Financial!G8<=8.8, "Moderate", "Not Recommended")) -> Not Recommended | K1: Graphical Results
C2: Solar PV System & Financial Report Analysis
A3: DATE: | B3: =TODAY() -> 46075
A4: Given Details | E4: System Output Idea | I4: Energy Production
A5: Parameters | B5: Value | C5: Units | E5: Paramters | F5: Value | G5: Units | I5: Paramters | J5: Value | K5: Units
A6: Yearly units Consumed | B6: =Inputs!D5 -> 365 | C6: kWh/year | E6: For Solar Watts (W) | F6: =Inputs!D12 -> 550 | G6: W | I6: Annual Energy Generation | J6: =Technical!E5 -> 798.4375 | K6: kWh/year
A7: Monthly Units Consumed | B7: =Inputs!D6 -> 30.416667 | C7: kWh/month | E7: Solar System Size | F7: =Inputs!D11 -> 0.44357639 | G7: kW | I7: Monthly Energy Generation | J7: =Technical!E6 -> 66.536458 | K7: kWh/month
A8: Daily Units Consumed | B8: =Inputs!D7 -> 1.0138889 | C8: kWh/day | E8: No. Of Panels Required | F8: =Technical!E8 -> 0.80650253 | I8: Daily Energy Generation | J8: =Technical!E7 -> 2.2178819 | K8: kWh/day
A9: Location | B9: PAKISTAN | E9: CostperkW | F9: =Financial!G14 -> 175000 | G9: Rs.
A10: Peak Sun Hours | B10: =Inputs!D9 -> 5 | C10: hrs. | E10: Total Panels Cost | F10: =Financial!D5 -> 77625.868 | G10: Rs. | I10: Excess Energy/Units Generate | J10: =Technical!E11 -> 433.4375 | K10: kWh/year
A11: System Efficiency | B11: =Inputs!D10 -> 0.8 | E11: Inverter Size | F11: =Technical!E9 -> 0.66536458 | G11: kW
A14: Investment & Coverage
A15: Parameters | B15: Value | C15: Units
A16: Total System Cost Required | B16: =Financial!D10 -> 382625.87 | C16: Rs.
A17: Tarriff Rate | B17: =Financial!G12 -> 40 | C17: Rs./Unit
A18: WAPDA Bill Cut-off Price | B18: =Financial!G5 -> 14600 | C18: Rs.
A19: Export Unit Rate | B19: =Financial!G13 -> 20 | C19: Rs./Unit
A20: Earn Money from Export Units | B20: =Financial!G6 -> 8668.75 | C20: Rs.
A21: Total Save Money | B21: =Financial!G7 -> 23268.75 | C21: Rs.
A23: Payback Period | B23: =Financial!G8 -> 16.443765 | C23: Years
A24: ROI | B24: =Financial!G9 -> 6.0813322 | C24: %/Year
A26: Daily Coverage | B26: =(B8/J8) * 100 -> 45.714286 | C26: %/day
A28: Sustainable Environment | E28: Final Verdict | F28: This PV System calculations and analysis is estimated based on "Pakistan" assumptions. It may varies and get real-time idea by visit the site with all scenarios will be considered.
A29: Parameters | B29: Value | C29: Units
A30: Reduce Carbon Dioxide Emission | B30: =Technical!E14 -> 399.21875 | C30: kg
A31: 25-Year Carbon Dioxide Emission Reduce | B31: =Technical!E15 -> 9980.4688 | C31: kg

Sheet Feasible
A1: SunEnergy Value | B1: #VALUE!
A3: Check (NPV) Feasiblity | C3: In this sheet, we check the feasibility behaviour of our system. That, tells our investment in safe hand or not?
A6: Data | B6: Value | C6: Description
A7: Discount Rate (r) | B7: 0.1 | C7: If I put my investment in bank, then per year it gives me 10% profit which is known as "Bench mark". We compare both senarios, to deposit money in bank vs investment in installed solar system.
A8: Annual Savings (Includes bill saving + Export Units Revenue) Money | B8: =Financial!G7 -> 23268.75
A9: Operating & Maintenace Cost (For System) | B9: =(B8/10) -> 2326.875
A10: Initial Investment (Total System Cost) | B10: =Financial!D10 -> 382625.87
A11: Total Cash Flow | B11: =(B8 - B9) -> 20941.875
A12: NPV (Net Present Value) | B12: =(B11 / (1+B7)^32) - B10 -> -381634.01
A14: Final Remarks | B14: =IF(B12>0, "Feasible", IF(B12=0, "Break Even", "Not Feasible")) -> Not Feasible
A16: Check IRR | C16: Actual rate of return, in which net present value equals to zero. The system is feasible only, if IRR greater than discount rate.
A18: NPV | B18: 0
A19: Total Cash Flow | B19: =B11 -> 20941.875
A20: Initial Investment (Total System Cost) | B20: =B10 -> 382625.87
A21: IRR | B21: =(((B19/B20)^(1/32)) - 1) * 100 -> -8.6791304
A23: Final Remarks | B23: =IF(B21>B7, "Feasible", IF(B21=B7, "Break Even", "Not Feasible")) -> Not Feasible
A25: Check LCOE | C25: Check the levelized Cost of Energy, gives an idea how much charge our system gives 1 Unit(kWh) cost and compare with grid tarriff rate.
A26: Data | B26: Value | C26: Units
A27: Total Life Cycle of solar system | B27: =Financial!D12 -> 25 | C27: Years
A28: Annually Units/Energy Generation | B28: =Technical!E5 -> 798.4375 | C28: kWh/Year
A29: Total Life-Time Units/Energy Generation | B29: =(B28 * B27) -> 19960.938 | C29: kWh/Life-Time
A31: LCOE | B31: =(B20/B29) -> 19.168732 | C31: Rs.
A32: Check Tarriff Rate
A33: Data | B33: Value | C33: Units
A34: Tarriff Rate In Pakistan | B34: 40 | C34: Rs.
A36: Final Remarks | B36: =IF(B31<B34, "Feasible", IF(B31=B34, "Break Even", "Not Feasible")) -> Feasible
A38: Environmental Monetization
A39: Data | B39: Value | C39: Units
A40: 1 Ton | B40: 1000 | C40: kg
A41: Reduced Carbon Dioxide Emission Annually | B41: =Technical!E5 * Inputs!D15 -> 399.21875 | C41: kg/kWh/Year
A42: 25 -Year Reduced Carbon Dioxide Emission | B42: =Feasible!B41 * 25 -> 9980.4688 | C42: kg/kWh/25Years
A43: 1 Ton Carbon Dioxide Reduced Price | B43: 2800 | C43: Rs.
A44: Annually Carbon Credit
A45: How much ton your system reduced carbon dioxide emission annually | B45: =(B41/B40) -> 0.39921875 | C45: Ton
A46: Carbon Credit Price for your system | B46: =(B45 * B43) -> 1117.8125 | C46: Rs./Year
A47: Over 25 Years
A48: How much ton your system reduced carbon dioxide emission over 25Years | B48: =(B42/B40) -> 9.9804688 | C48: Ton
A49: Carbon Credit Price for your system | B49: =(B48 * B43) -> 27945.312 | C49: Rs. / Year

Sheet Scoring
A1: SunEnergy Value | B1: #VALUE!
B4: Sustainability Factors
A5: Factors | B5: Values | C5: Units | D5: Score
A6: Carbon Dioxide Emission Annually | B6: =Environmental!B5 -> 399.21875 | C6: kg/Year | D6: =IF(B6<200, 25, IF(B6<=500, 50, IF(B6<=1000, 75, 100))) -> 50
A7: For 25 Years Carbon Dioxide Emission | B7: =Environmental!B6 -> 9980.4688 | C7: kg/25Year | D7: =IF(B7<5000, 25, IF(B7<=7500, 50, IF(B7<=10000, 75, 100))) -> 75
A8: Renewable Solar Load Coverage | B8: ='Visual Dashboard'!B26 -> 45.714286 | C8: %/day | D8: =IF(B8<30, 25, IF(B8<=60, 50, IF(B8<=90, 75, 100))) -> 50
A9: LCOE vs Grid Tarriff Rate | B9: =(Feasible!B31 / Feasible!B34) * 100 -> 47.921831 | C9: Difference (Solar unit cost / Grid Tarriff unit cost) | D9: =IF(B9<5, 25, IF(B9<=15, 50, IF(B9<=25, 75, 100))) -> 100
B11: Sustainability Index | C11: =SUM(D6:D9) / 4 -> 68.75 | D11: =IF(C11<60, "Low Sustainable", IF(C11<=75, "Moderate Sustainable", "Highly Sustainable")) -> Moderate Sustainable

Sheet Testing
A1: SunEnergy Value | B1: #VALUE!
B4: Testing & Validation
A5: Check Case
B6: Physical Module | F6: Economic Module
A7: Parameters | B7: Values | C7: Units | E7: Parameters | F7: Values | G7: Units
A8: Annually Units Consumed | B8: =Inputs!D5 -> 365 | C8: kWh/year | E8: Discount rate | F8: 0.1
A9: Monthly Units Consumed | B9: =Inputs!D6 -> 30.416667 | C9: kWh/month | E9: Initial Investment | F9: =Financial!D10 -> 382625.87 | G9: Rs.
A10: Daily Units Consumed | B10: =Inputs!D7 -> 1.0138889 | C10: kWh/day | E10: Annual Cash Flow | F10: =Feasible!B19 -> 20941.875 | G10: Rs.
A11: Peak Sun Hours (PSH) | B11: =Inputs!D9 -> 5 | C11: hrs. | E11: Net Present Value (NPV) | F11: =Feasible!B12 -> -381634.01 | G11: Rs.
A12: Solar System Efficiency | B12: =Inputs!D10 -> 0.8 | E12: Yearly Units Generation | F12: =Technical!E5 -> 798.4375 | G12: kWh/year
A13: Expanded PV Size | B13: =(B10/(B11*B12)*1.75) -> 0.44357639 | C13: kW | E13: Total Solar Life-Cycle | F13: =Financial!D12 -> 25 | G13: Years
A14: Solar Size (Watts) | B14: =Inputs!D12 -> 550 | C14: W | E14: Total Life Cycle Units Generate | F14: =F12 * F13 -> 19960.938 | G14: kWh/total life cycle
A15: No. of Panels Required | B15: =(B13 * 1000)/B14 -> 0.80650253 | E15: LCOE | F15: =F9 / F14 -> 19.168732 | G15: Rs.
A16: Inverter Size | B16: =B13 * 1.5 -> 0.66536458 | C16: kW | E16: Payback Period | F16: =Financial!G8 -> 16.443765 | G16: Years
E17: ROI | F17: =Financial!G9 -> 6.0813322 | G17: %/Year
